<manifest alg="2" build="2017.0.1.363" opt="false" iceEnabled="true" iceMarkupVersion="2" iceEnabledOptions="link,responsive,cachebuster" exportTarget="other" domain="123.ml" resolutions="1x" timestamp="1503010724509">
  <folder name="css">
    <file name="site_global.css" crc="443350757"/>
    <file name="index.css" crc="450723844" ref="index"/>
    <file name="nomq_index.css" crc="42649778" ref="index"/>
    <file name="about.css" crc="430569685" ref="about"/>
    <file name="nomq_about.css" crc="4264826959" ref="about"/>
    <file name="features.css" crc="61911547" ref="features"/>
    <file name="nomq_features.css" crc="283079612" ref="features"/>
  </folder>
  <folder name="scripts">
    <file name="jquery-1.8.3.min.js" crc="209076791" ref="index:about:features"/>
    <file name="museutils.js" crc="4148063285" ref="index:about:features"/>
    <file name="whatinput.js" crc="86476730" ref="index:about:features"/>
    <file name="museconfig.js" crc="172512987" ref="index:about:features"/>
    <file name="jquery.watch.js" crc="437028206" ref="index:about:features"/>
    <file name="jquery.museresponsive.js" crc="3991890305" ref="index:about:features"/>
    <file name="require.js" crc="4159430777" ref="index:about:features"/>
  </folder>
  <folder name="images">
    <file name="u439-4.png" crc="3936542878" ref="index"/>
    <file name="u484-4.png" crc="3864532300" ref="index"/>
    <file name="u128-4.png" crc="3974956829" ref="index"/>
    <file name="u128-42.png" crc="308122660" ref="index"/>
    <file name="u484-42.png" crc="56433853" ref="index"/>
    <file name="u439-42.png" crc="4053303994" ref="index"/>
    <file name="blank.gif" crc="4208392903" ref="index:about:features"/>
    <file name="u549-4.png" crc="3936542878" ref="about"/>
    <file name="u551-4.png" crc="3864532300" ref="about"/>
    <file name="u610-31.png" crc="3967237854" ref="about"/>
    <file name="u544-4.png" crc="3974956829" ref="about"/>
    <file name="u544-42.png" crc="308122660" ref="about"/>
    <file name="u551-42.png" crc="56433853" ref="about"/>
    <file name="u549-42.png" crc="4053303994" ref="about"/>
    <file name="u610-312.png" crc="66090748" ref="about"/>
    <file name="u674-4.png" crc="4076396428" ref="index"/>
    <file name="u674-42.png" crc="15544831" ref="index"/>
    <file name="u696-4.png" crc="4076396428" ref="about"/>
    <file name="u696-42.png" crc="15544831" ref="about"/>
    <file name="u730-4.png" crc="3936542878" ref="features"/>
    <file name="u723-4.png" crc="3864532300" ref="features"/>
    <file name="u726-4.png" crc="4076396428" ref="features"/>
    <file name="u728-4.png" crc="3974956829" ref="features"/>
    <file name="u728-42.png" crc="308122660" ref="features"/>
    <file name="u723-42.png" crc="56433853" ref="features"/>
    <file name="u726-42.png" crc="15544831" ref="features"/>
    <file name="u730-42.png" crc="4053303994" ref="features"/>
  </folder>
  <file name="index.html" crc="3765030724" seo="true" mt="1503010690534" redirect="true"/>
  <file name="about.html" crc="449763259" seo="true" mt="1503009924080" redirect="true"/>
  <file name="features.html" crc="192538903" seo="true" mt="1503009905766" redirect="true"/>
</manifest>